LICENSE.txt
MANIFEST.in
README.rst
setup.cfg
setup.py
cmsplugin_ss_grid/__init__.py
cmsplugin_ss_grid/cms_plugins.py
cmsplugin_ss_grid/fields.py
cmsplugin_ss_grid/forms.py
cmsplugin_ss_grid/models.py
cmsplugin_ss_grid/test.py
cmsplugin_ss_grid/widgets.py
cmsplugin_ss_grid.egg-info/PKG-INFO
cmsplugin_ss_grid.egg-info/SOURCES.txt
cmsplugin_ss_grid.egg-info/dependency_links.txt
cmsplugin_ss_grid.egg-info/top_level.txt
cmsplugin_ss_grid/migrations/0001_initial.py
cmsplugin_ss_grid/migrations/0002_auto_20171211_1043.py
cmsplugin_ss_grid/migrations/__init__.py
cmsplugin_ss_grid/static/colorpicker/LICENSE
cmsplugin_ss_grid/static/colorpicker/MIT-LICENSE.txt
cmsplugin_ss_grid/static/colorpicker/README.md
cmsplugin_ss_grid/static/colorpicker/colorpicker.js
cmsplugin_ss_grid/static/colorpicker/css/colorpicker.css
cmsplugin_ss_grid/static/colorpicker/images/grabber.png
cmsplugin_ss_grid/static/colorpicker/images/gradient_grabber.png
cmsplugin_ss_grid/static/colorpicker/images/gradient_input.png
cmsplugin_ss_grid/static/colorpicker/images/indic.gif
cmsplugin_ss_grid/static/colorpicker/images/overlay.png
cmsplugin_ss_grid/static/colorpicker/images/select.gif
cmsplugin_ss_grid/static/colorpicker/images/select.png
cmsplugin_ss_grid/static/colorpicker/images/select2.png
cmsplugin_ss_grid/static/colorpicker/images/select3.png
cmsplugin_ss_grid/static/colorpicker/images/select4.png
cmsplugin_ss_grid/static/colorpicker/images/select_hue.png
cmsplugin_ss_grid/static/colorpicker/images/submit.png
cmsplugin_ss_grid/templates/cmsplugin_ss_grid/cell.html
cmsplugin_ss_grid/templates/cmsplugin_ss_grid/container.html